{
  "name": "Harvey Atkins",
  "age": 64,
  "address": {
    "street": "Hejguj Extension",
    "city": "Balofke",
    "state": "NM",
    "zip": "45367"
  },
  "contact": {
    "phone": "(775) 903-7715",
    "servicePhone": "800812171"
  },
  "birthday": "1969-03-30T20:54:35.607Z",
  "ip": "215.240.26.207",
  "foo": "bar",
  "profile": {
    "about": "Kokfe wola sogbu gajgi ogogifti uge puksurat ofefefor ili coc zekabo lu nimod obero. Rocak mizdep ode zo dupza cosekve uma kow nahovca netteg meni icumaba ul fekec ve fetmofij omvo. Miwu did va mahelka ludboce carsi rumsul nir di zabve kure turu ses duduzoaj.",
    "bio": "Tughop viwezgat zazufop ihnu mumcidez rehtiv ovdudol hegso iguba bumenze gefjeud di gak. Wi totnojcij viftete mita goco caalwuw wuj zumod fozole nehafzah zidawew gijowov weaja di vas emikmi pujfi. Ejopawop tubiwo ut dotubu sogole lilcodniz pevjam kehabco du kojamniz ben ma up er akidu."
  },
  "apiKey": "f85956d08892ad741281b367fc137ab60ccb0568b7ba4e89bfd204071068396f",
  "currency": {
    "code": "HKD",
    "name": "Hong Kong Dollar"
  }
}