{
  "name": "Gavin Alvarado",
  "age": 50,
  "address": {
    "street": "Rinbop Grove",
    "city": "Vohovbag",
    "state": "MD",
    "zip": "19593"
  },
  "contact": {
    "phone": "(642) 607-5105",
    "servicePhone": "800668487"
  },
  "birthday": "1968-04-12T15:27:22.450Z",
  "ip": "223.211.149.84",
  "foo": "bar",
  "profile": {
    "about": "Bab zimna pe wisfo op heluza ha vizginoj ocdiba jak luiw jousjub riafeahi lu ga mig. Dol ajoeduij fam ipuso vuimi fu men tentum gaf aloismin vapid ebuuc cop rejgahpa tajwesum afe fojje. Ba mu wabje beewakiw se ma uwkak hoj kuvuram vah mokni bovouf taroni ko cuacu of. Hihucupi ujbit somin tafiri ojutun zuwitug me wokti bifo reez utu uj ja ga fak zol faes nujecu. Worcinhe pedabte zi fuwus po ga nekiruj ge rir hemse ferzofuz gopcih hej. Omsokso tovuka mi si oturucod sokvaheb hatze fanar jelocooki ilho sekjawe dikas.",
    "bio": "Jo sigmumu beuw buwzepu oksof joulo did muzko noznon aziolaku pi polarvef rekkemjan riuhaid pow uhosu va. Han mohmob sadmapfib vapgu cofohed sita dugof vuf bapbuzwec rilok junu gebvoko. Casur opwijoj kuc aroufa jav awi haek kovlop ugobi jotcazim tesirus pimduep."
  },
  "apiKey": "66e2116f4ab19ecf9a65604b48aa094a5f7ff54f51acd867ec1e03bd10c3c752",
  "currency": {
    "code": "NOK",
    "name": "Norway Krone"
  }
}