{
  "name": "Vera Scott",
  "age": 33,
  "address": {
    "street": "Licwol Avenue",
    "city": "Icajeodi",
    "state": "CA",
    "zip": "95667"
  },
  "contact": {
    "phone": "(821) 372-6338",
    "servicePhone": "800999231"
  },
  "birthday": "1980-10-23T19:16:54.559Z",
  "ip": "7.200.132.47",
  "foo": "bar",
  "profile": {
    "about": "Guw menac tedonvo ojauc noedmin mulaz wol ib fomva ukeino zibuza pe awo fodsihjoz taviewu. Hok emjec janhe ziegozap go tudife ud iha sah itipa ku iziil ewokad rouzsez lon nipkef. Dimeos fitapeci ve utaoropu ufatebar metgul wehezwap tulkenir wohubige ji penofcug neb. Ha paobe koru duele tocan esrusu suza guhgooh igazim degher te daba ufegecmat loisuw ligdul nevjatno gussam feul. Ri cune kaeh zi ag ericusu hum sagva zew tahapep votagihe hukso.",
    "bio": "Agimiise coti vizuake gohkubo fumbu sekor obhu ropez gul narusu jidozut so zo hifcew. Ar pog ali pajtuk igaji ibifo ul livdorog javogefol jur fov liw omuce. Raz ut lesu pazedso ap va jaavunil vujjo ehdapori wisucpuv esmoner kipodi patopcoc pimi. Mubrarug nehe haub kubje one na baj duguhi zi cufkec iwemec fiz melij jomduve tudsozca uzeci."
  },
  "apiKey": "b594996d19e88a53fb6131bbcbcf1216ff44b3585153c133f24d0fb181ee8eda",
  "currency": {
    "code": "XCD",
    "name": "East Caribbean Dollar"
  }
}